pipecat_awaazai/__init__.py
pipecat_awaazai/serializer.py
pipecat_awaazai-0.1.0.dist-info/METADATA
pipecat_awaazai-0.1.0.dist-info/WHEEL
pipecat_awaazai-0.1.0.dist-info/licenses/LICENSE
pipecat_awaazai-0.1.0.dist-info/RECORD
