Metadata-Version: 2.4
Name: pipecat-awaazai
Version: 0.1.0
Summary: AwaazAI WebSocket frame serializer for Pipecat for hosting agents on telephony
Project-URL: Homepage, https://github.com/awaazde/pipecat-awaazai
Project-URL: Repository, https://github.com/awaazde/pipecat-awaazai
Project-URL: Issues, https://github.com/awaazde/pipecat-awaazai/issues
Author: AwaazAI Team
License: MIT
License-File: LICENSE
Classifier: Development Status :: 3 - Alpha
Classifier: Intended Audience :: Developers
Classifier: License :: OSI Approved :: MIT License
Classifier: Programming Language :: Python :: 3
Classifier: Programming Language :: Python :: 3.9
Classifier: Programming Language :: Python :: 3.10
Classifier: Programming Language :: Python :: 3.11
Classifier: Programming Language :: Python :: 3.12
Requires-Python: >=3.9
Requires-Dist: deepgram-sdk<4.0.0
Requires-Dist: pipecat-ai[silero,websocket]
Requires-Dist: pydantic
Requires-Dist: python-dotenv
Requires-Dist: uvicorn[standard]
